cailculator_mcp/__init__.py
cailculator_mcp/auth.py
cailculator_mcp/batch_processor.py
cailculator_mcp/clifford_algebras_standard_lib_backup.py
cailculator_mcp/clifford_verified.py
cailculator_mcp/config.py
cailculator_mcp/data_loaders.py
cailculator_mcp/e8_lattice.py
cailculator_mcp/e8_pathion_bridge.py
cailculator_mcp/e8_utils.py
cailculator_mcp/hypercomplex.py
cailculator_mcp/patterns.py
cailculator_mcp/quant_indicators.py
cailculator_mcp/regime_detection.py
cailculator_mcp/server.py
cailculator_mcp/terminology.py
cailculator_mcp/tools.py
cailculator_mcp/transforms.py
cailculator_mcp/visualizations.py
cailculator_mcp/weyl_orbit_experiment.py
cailculator_mcp/zdtp/__init__.py
cailculator_mcp/zdtp/gateways.py
cailculator_mcp/zdtp/protocol.py
cailculator_mcp-1.4.2.dist-info/licenses/LICENSE
cailculator_mcp-1.4.2.dist-info/METADATA
cailculator_mcp-1.4.2.dist-info/WHEEL
cailculator_mcp-1.4.2.dist-info/entry_points.txt
cailculator_mcp-1.4.2.dist-info/top_level.txt
cailculator_mcp-1.4.2.dist-info/RECORD
