Metadata-Version: 2.4
Name: cailculator-mcp
Version: 1.4.2
Summary: CAILculator MCP Server - High-dimensional data analysis with dual algebra frameworks
Author-email: Paul Chavez <paul@chavezailabs.com>
License: MIT
Project-URL: Homepage, https://github.com/pchavez2029/cailculator-mcp
Project-URL: Documentation, https://github.com/pchavez2029/cailculator-mcp#readme
Project-URL: Repository, https://github.com/pchavez2029/cailculator-mcp
Project-URL: Issues, https://github.com/pchavez2029/cailculator-mcp/issues
Classifier: Development Status :: 5 - Production/Stable
Classifier: Intended Audience :: Science/Research
Classifier: Intended Audience :: Developers
Classifier: License :: OSI Approved :: MIT License
Classifier: Programming Language :: Python :: 3
Classifier: Programming Language :: Python :: 3.10
Classifier: Programming Language :: Python :: 3.11
Classifier: Programming Language :: Python :: 3.12
Classifier: Topic :: Scientific/Engineering :: Mathematics
Classifier: Topic :: Scientific/Engineering :: Physics
Requires-Python: >=3.10
License-File: LICENSE
Requires-Dist: mcp>=0.9.0
Requires-Dist: numpy>=1.24.0
Requires-Dist: scipy>=1.10.0
Requires-Dist: pandas>=2.0.0
Requires-Dist: pydantic>=2.0.0
Requires-Dist: pydantic-settings>=2.0.0
Requires-Dist: python-dotenv>=1.0.0
Requires-Dist: httpx>=0.27.0
Requires-Dist: matplotlib>=3.7.0
Requires-Dist: networkx>=3.0
Requires-Dist: hypercomplex>=0.3.4
Requires-Dist: clifford>=1.5.0
Requires-Dist: pandas-ta>=0.3.14b
Requires-Dist: openpyxl>=3.1.0
Provides-Extra: dev
Requires-Dist: pytest>=7.0.0; extra == "dev"
Requires-Dist: pytest-asyncio>=0.21.0; extra == "dev"
Requires-Dist: black>=23.0.0; extra == "dev"
Requires-Dist: ruff>=0.1.0; extra == "dev"
Provides-Extra: premium
Requires-Dist: plotly>=5.18.0; extra == "premium"
Requires-Dist: kaleido>=0.2.1; extra == "premium"
Provides-Extra: web
Requires-Dist: gradio>=4.0.0; extra == "web"
Provides-Extra: http
Requires-Dist: aiohttp>=3.9.0; extra == "http"
Dynamic: license-file
